{
  "id": "banana-appam",
  "code": "OSR110",
  "name": "Banana appam",
  "alternateNames": [],
  "caloriesPer100g": 469.81,
  "energyKj": 1938.6,
  "proteinPer100g": 1.17,
  "carbsPer100g": 20.06,
  "fatPer100g": 42.53,
  "fiberPer100g": 0.67,
  "freeSugarPer100g": 9.95,
  "saturatedFatPer100g": 5727.34,
  "monounsaturatedFatPer100g": 8540.8,
  "polyunsaturatedFatPer100g": 26201.35,
  "cholesterolPer100g": 0,
  "calciumPer100g": 13.74,
  "phosphorusPer100g": 27.05,
  "magnesiumPer100g": 19.47,
  "sodiumPer100g": 20.14,
  "potassiumPer100g": 142.99,
  "ironPer100g": 0.77,
  "copperPer100g": 0.07,
  "zincPer100g": 0.09,
  "seleniumPer100g": 0.44,
  "chromiumPer100g": 0,
  "manganesePer100g": 0.18,
  "molybdenumPer100g": 0,
  "vitaminAPer100g": 0,
  "vitaminEPer100g": 20.46,
  "vitaminD2Per100g": 0.11,
  "vitaminD3Per100g": 0,
  "vitaminDPer100g": 0.11,
  "vitaminK1Per100g": 3.04,
  "vitaminK2Per100g": 0,
  "folatePer100g": 4.75,
  "vitaminB1Per100g": 0.02,
  "vitaminB2Per100g": 0.01,
  "vitaminB3Per100g": 0.31,
  "vitaminB5Per100g": 0.08,
  "vitaminB6Per100g": 0.17,
  "vitaminB7Per100g": 0.34,
  "vitaminB9Per100g": 4.75,
  "vitaminCPer100g": 1.39,
  "carotenoidsPer100g": 49.71,
  "standardServings": {
    "serving": 100
  },
  "source": "open_source_recipes",
  "primaryCategory": "uncategorized",
  "tags": [],
  "searchTerms": [
    "banana appam",
    "banana",
    "appam"
  ]
}