{
  "id": "beans-and-macaroni",
  "code": "BFP154",
  "name": "Beans and macaroni",
  "alternateNames": [],
  "caloriesPer100g": 136.08,
  "energyKj": 569.73,
  "proteinPer100g": 4.58,
  "carbsPer100g": 14.24,
  "fatPer100g": 7.01,
  "fiberPer100g": 2.05,
  "freeSugarPer100g": 1.68,
  "saturatedFatPer100g": 4248.25,
  "monounsaturatedFatPer100g": 1774.3,
  "polyunsaturatedFatPer100g": 416.38,
  "cholesterolPer100g": 19.67,
  "calciumPer100g": 86.86,
  "phosphorusPer100g": 126.74,
  "magnesiumPer100g": 27.05,
  "sodiumPer100g": 182.79,
  "potassiumPer100g": 221.16,
  "ironPer100g": 0.75,
  "copperPer100g": 0.09,
  "zincPer100g": 0.62,
  "seleniumPer100g": 3.96,
  "chromiumPer100g": 0,
  "manganesePer100g": 0.26,
  "molybdenumPer100g": 0.02,
  "vitaminAPer100g": 77.42,
  "vitaminEPer100g": 0.29,
  "vitaminD2Per100g": 3.54,
  "vitaminD3Per100g": 0,
  "vitaminDPer100g": 3.54,
  "vitaminK1Per100g": 12.4,
  "vitaminK2Per100g": 0,
  "folatePer100g": 32.5,
  "vitaminB1Per100g": 0.06,
  "vitaminB2Per100g": 0.06,
  "vitaminB3Per100g": 0.95,
  "vitaminB5Per100g": 0.34,
  "vitaminB6Per100g": 0.22,
  "vitaminB7Per100g": 3.31,
  "vitaminB9Per100g": 32.5,
  "vitaminCPer100g": 6.51,
  "carotenoidsPer100g": 1988.59,
  "standardServings": {
    "serving": 100
  },
  "source": "bfp_manual",
  "primaryCategory": "uncategorized",
  "tags": [],
  "searchTerms": [
    "beans and macaroni",
    "beans",
    "and",
    "macaroni"
  ]
}