{
  "id": "cabbage-rolls-curry-pattagobhi-rolls-curry",
  "code": "BFP262",
  "name": "Cabbage rolls (curry) ((Pattagobhi rolls)(curry))",
  "alternateNames": [],
  "caloriesPer100g": 124.63,
  "energyKj": 518.75,
  "proteinPer100g": 5.76,
  "carbsPer100g": 7.03,
  "fatPer100g": 8.17,
  "fiberPer100g": 2.35,
  "freeSugarPer100g": 3.81,
  "saturatedFatPer100g": 2530.9,
  "monounsaturatedFatPer100g": 2248.07,
  "polyunsaturatedFatPer100g": 2858.41,
  "cholesterolPer100g": 18.79,
  "calciumPer100g": 29.82,
  "phosphorusPer100g": 75.47,
  "magnesiumPer100g": 26.41,
  "sodiumPer100g": 123.98,
  "potassiumPer100g": 425.86,
  "ironPer100g": 0.95,
  "copperPer100g": 0.14,
  "zincPer100g": 0.98,
  "seleniumPer100g": 0.93,
  "chromiumPer100g": 0,
  "manganesePer100g": 0.33,
  "molybdenumPer100g": 0.03,
  "vitaminAPer100g": 14.19,
  "vitaminEPer100g": 3.2,
  "vitaminD2Per100g": 0.59,
  "vitaminD3Per100g": 0,
  "vitaminDPer100g": 0.59,
  "vitaminK1Per100g": 26.14,
  "vitaminK2Per100g": 0,
  "folatePer100g": 23.38,
  "vitaminB1Per100g": 0.25,
  "vitaminB2Per100g": 0.08,
  "vitaminB3Per100g": 1.89,
  "vitaminB5Per100g": 0.33,
  "vitaminB6Per100g": 0.16,
  "vitaminB7Per100g": 2.45,
  "vitaminB9Per100g": 23.38,
  "vitaminCPer100g": 18.48,
  "carotenoidsPer100g": 499.78,
  "standardServings": {
    "serving": 100
  },
  "source": "bfp_manual",
  "primaryCategory": "uncategorized",
  "tags": [],
  "searchTerms": [
    "cabbage rolls (curry) ((pattagobhi rolls)(curry))",
    "cabbage",
    "rolls",
    "(curry)",
    "((pattagobhi",
    "rolls)(curry))"
  ]
}