{
  "id": "chocolate-eggless-cake",
  "code": "BFP495",
  "name": "Chocolate eggless cake",
  "alternateNames": [],
  "caloriesPer100g": 312.01,
  "energyKj": 1308.4,
  "proteinPer100g": 6.66,
  "carbsPer100g": 43.45,
  "fatPer100g": 13.19,
  "fiberPer100g": 0.32,
  "freeSugarPer100g": 34.2,
  "saturatedFatPer100g": 8211.5,
  "monounsaturatedFatPer100g": 3590.5,
  "polyunsaturatedFatPer100g": 461.79,
  "cholesterolPer100g": 35.49,
  "calciumPer100g": 185.38,
  "phosphorusPer100g": 228.05,
  "magnesiumPer100g": 51.12,
  "sodiumPer100g": 196.61,
  "potassiumPer100g": 317.29,
  "ironPer100g": 0.95,
  "copperPer100g": 0.25,
  "zincPer100g": 1.11,
  "seleniumPer100g": 1.75,
  "chromiumPer100g": 0,
  "manganesePer100g": 0.07,
  "molybdenumPer100g": 0,
  "vitaminAPer100g": 147.71,
  "vitaminEPer100g": 0.32,
  "vitaminD2Per100g": 0.78,
  "vitaminD3Per100g": 0,
  "vitaminDPer100g": 0.78,
  "vitaminK1Per100g": 1.06,
  "vitaminK2Per100g": 0,
  "folatePer100g": 12.84,
  "vitaminB1Per100g": 0.08,
  "vitaminB2Per100g": 0.28,
  "vitaminB3Per100g": 0.36,
  "vitaminB5Per100g": 0.58,
  "vitaminB6Per100g": 0.05,
  "vitaminB7Per100g": 2.36,
  "vitaminB9Per100g": 12.84,
  "vitaminCPer100g": 2.33,
  "carotenoidsPer100g": 127.63,
  "standardServings": {
    "serving": 100
  },
  "source": "bfp_manual",
  "primaryCategory": "uncategorized",
  "tags": [],
  "searchTerms": [
    "chocolate eggless cake",
    "chocolate",
    "eggless",
    "cake"
  ]
}