{
  "id": "green-chickpeas-pulao-choliya-pulao-hare-chane-ka-pulao",
  "code": "ASC121",
  "name": "Green chickpeas pulao (Choliya pulao/Hare chane ka pulao)",
  "alternateNames": [],
  "caloriesPer100g": 173.43,
  "energyKj": 722.95,
  "proteinPer100g": 4.88,
  "carbsPer100g": 27.57,
  "fatPer100g": 4.82,
  "fiberPer100g": 3.15,
  "freeSugarPer100g": 2.48,
  "saturatedFatPer100g": 587.75,
  "monounsaturatedFatPer100g": 1007.47,
  "polyunsaturatedFatPer100g": 2846.6,
  "cholesterolPer100g": 0,
  "calciumPer100g": 18.94,
  "phosphorusPer100g": 72.14,
  "magnesiumPer100g": 21.62,
  "sodiumPer100g": 170.05,
  "potassiumPer100g": 164.6,
  "ironPer100g": 0.95,
  "copperPer100g": 0.17,
  "zincPer100g": 0.7,
  "seleniumPer100g": 0.35,
  "chromiumPer100g": 0,
  "manganesePer100g": 0.98,
  "molybdenumPer100g": 0.02,
  "vitaminAPer100g": 0,
  "vitaminEPer100g": 2,
  "vitaminD2Per100g": 0.24,
  "vitaminD3Per100g": 0,
  "vitaminDPer100g": 0.24,
  "vitaminK1Per100g": 2.98,
  "vitaminK2Per100g": 0,
  "folatePer100g": 84.14,
  "vitaminB1Per100g": 0.11,
  "vitaminB2Per100g": 0.05,
  "vitaminB3Per100g": 0.84,
  "vitaminB5Per100g": 0.39,
  "vitaminB6Per100g": 0.14,
  "vitaminB7Per100g": 0.45,
  "vitaminB9Per100g": 84.14,
  "vitaminCPer100g": 1.52,
  "carotenoidsPer100g": 36.02,
  "standardServings": {
    "serving": 100
  },
  "source": "asc_manual",
  "primaryCategory": "uncategorized",
  "tags": [],
  "searchTerms": [
    "green chickpeas pulao (choliya pulao/hare chane ka pulao)",
    "green",
    "chickpeas",
    "pulao",
    "(choliya",
    "pulao/hare",
    "chane",
    "ka",
    "pulao)"
  ]
}