{
  "id": "lemonade",
  "code": "ASC008",
  "name": "Lemonade",
  "alternateNames": [],
  "caloriesPer100g": 20.8,
  "energyKj": 88.66,
  "proteinPer100g": 0.03,
  "carbsPer100g": 5.48,
  "fatPer100g": 0.01,
  "fiberPer100g": 0.02,
  "freeSugarPer100g": 5.47,
  "saturatedFatPer100g": 4.65,
  "monounsaturatedFatPer100g": 0.04,
  "polyunsaturatedFatPer100g": 5.3,
  "cholesterolPer100g": 0,
  "calciumPer100g": 1.84,
  "phosphorusPer100g": 0.67,
  "magnesiumPer100g": 0.73,
  "sodiumPer100g": 28.52,
  "potassiumPer100g": 5.73,
  "ironPer100g": 0.05,
  "copperPer100g": 0.01,
  "zincPer100g": 0.01,
  "seleniumPer100g": 0.07,
  "chromiumPer100g": 0,
  "manganesePer100g": 0,
  "molybdenumPer100g": 0,
  "vitaminAPer100g": 0,
  "vitaminEPer100g": 0,
  "vitaminD2Per100g": 0.01,
  "vitaminD3Per100g": 0,
  "vitaminDPer100g": 0.01,
  "vitaminK1Per100g": 0.47,
  "vitaminK2Per100g": 0,
  "folatePer100g": 0.6,
  "vitaminB1Per100g": 0,
  "vitaminB2Per100g": 0,
  "vitaminB3Per100g": 0.01,
  "vitaminB5Per100g": 0.01,
  "vitaminB6Per100g": 0,
  "vitaminB7Per100g": 0.01,
  "vitaminB9Per100g": 0.6,
  "vitaminCPer100g": 1.51,
  "carotenoidsPer100g": 53.7,
  "standardServings": {
    "serving": 100
  },
  "source": "asc_manual",
  "primaryCategory": "uncategorized",
  "tags": [],
  "searchTerms": [
    "lemonade"
  ]
}