{
  "id": "methi-parantha-paratha",
  "code": "BFP110",
  "name": "Methi parantha/paratha",
  "alternateNames": [],
  "caloriesPer100g": 148.36,
  "energyKj": 618.37,
  "proteinPer100g": 4.27,
  "carbsPer100g": 22.19,
  "fatPer100g": 4.34,
  "fiberPer100g": 5.09,
  "freeSugarPer100g": 2.44,
  "saturatedFatPer100g": 558.79,
  "monounsaturatedFatPer100g": 809.69,
  "polyunsaturatedFatPer100g": 2655.25,
  "cholesterolPer100g": 0,
  "calciumPer100g": 65.85,
  "phosphorusPer100g": 112.69,
  "magnesiumPer100g": 54.87,
  "sodiumPer100g": 48.36,
  "potassiumPer100g": 193.92,
  "ironPer100g": 2.42,
  "copperPer100g": 0.21,
  "zincPer100g": 1.04,
  "seleniumPer100g": 15.87,
  "chromiumPer100g": 0.01,
  "manganesePer100g": 1.17,
  "molybdenumPer100g": 0.02,
  "vitaminAPer100g": 0,
  "vitaminEPer100g": 1.96,
  "vitaminD2Per100g": 4.68,
  "vitaminD3Per100g": 0,
  "vitaminDPer100g": 4.68,
  "vitaminK1Per100g": 80.9,
  "vitaminK2Per100g": 0,
  "folatePer100g": 31.2,
  "vitaminB1Per100g": 0.16,
  "vitaminB2Per100g": 0.09,
  "vitaminB3Per100g": 0.94,
  "vitaminB5Per100g": 0.44,
  "vitaminB6Per100g": 0.18,
  "vitaminB7Per100g": 1.89,
  "vitaminB9Per100g": 31.2,
  "vitaminCPer100g": 13.85,
  "carotenoidsPer100g": 2462.55,
  "standardServings": {
    "serving": 100
  },
  "source": "bfp_manual",
  "primaryCategory": "uncategorized",
  "tags": [],
  "searchTerms": [
    "methi parantha/paratha",
    "methi",
    "parantha/paratha"
  ]
}