{
  "id": "minced-meat-patties",
  "code": "ASC411",
  "name": "Minced meat patties",
  "alternateNames": [],
  "caloriesPer100g": 265.72,
  "energyKj": 1101.4,
  "proteinPer100g": 6.88,
  "carbsPer100g": 15.25,
  "fatPer100g": 19.57,
  "fiberPer100g": 0.77,
  "freeSugarPer100g": 0.88,
  "saturatedFatPer100g": 3643.07,
  "monounsaturatedFatPer100g": 4807.12,
  "polyunsaturatedFatPer100g": 9927.14,
  "cholesterolPer100g": 81.36,
  "calciumPer100g": 19.23,
  "phosphorusPer100g": 96.83,
  "magnesiumPer100g": 13.2,
  "sodiumPer100g": 252.18,
  "potassiumPer100g": 119.59,
  "ironPer100g": 0.93,
  "copperPer100g": 0.07,
  "zincPer100g": 0.98,
  "seleniumPer100g": 3.64,
  "chromiumPer100g": 0,
  "manganesePer100g": 0.16,
  "molybdenumPer100g": 0.01,
  "vitaminAPer100g": 34.77,
  "vitaminEPer100g": 7.66,
  "vitaminD2Per100g": 1.41,
  "vitaminD3Per100g": 0.2,
  "vitaminDPer100g": 1.61,
  "vitaminK1Per100g": 1.85,
  "vitaminK2Per100g": 2.78,
  "folatePer100g": 12.61,
  "vitaminB1Per100g": 0.06,
  "vitaminB2Per100g": 0.06,
  "vitaminB3Per100g": 1.17,
  "vitaminB5Per100g": 0.51,
  "vitaminB6Per100g": 0.08,
  "vitaminB7Per100g": 4.74,
  "vitaminB9Per100g": 12.61,
  "vitaminCPer100g": 1.21,
  "carotenoidsPer100g": 113.5,
  "standardServings": {
    "serving": 100
  },
  "source": "asc_manual",
  "primaryCategory": "uncategorized",
  "tags": [],
  "searchTerms": [
    "minced meat patties",
    "minced",
    "meat",
    "patties"
  ]
}