{
  "id": "moti-mahal-dal-urad-rajmah-mix-dal",
  "code": "ASC160",
  "name": "Moti mahal dal (Urad rajmah mix dal)",
  "alternateNames": [],
  "caloriesPer100g": 103.13,
  "energyKj": 428.47,
  "proteinPer100g": 3.93,
  "carbsPer100g": 8.74,
  "fatPer100g": 5.66,
  "fiberPer100g": 3.38,
  "freeSugarPer100g": 1.7,
  "saturatedFatPer100g": 1001.32,
  "monounsaturatedFatPer100g": 1157.9,
  "polyunsaturatedFatPer100g": 3158.37,
  "cholesterolPer100g": 1.92,
  "calciumPer100g": 38.13,
  "phosphorusPer100g": 74.56,
  "magnesiumPer100g": 33.51,
  "sodiumPer100g": 157.61,
  "potassiumPer100g": 246.09,
  "ironPer100g": 1.05,
  "copperPer100g": 0.13,
  "zincPer100g": 0.55,
  "seleniumPer100g": 3.92,
  "chromiumPer100g": 0,
  "manganesePer100g": 0.35,
  "molybdenumPer100g": 0.06,
  "vitaminAPer100g": 7.52,
  "vitaminEPer100g": 2.41,
  "vitaminD2Per100g": 4.9,
  "vitaminD3Per100g": 0,
  "vitaminDPer100g": 4.9,
  "vitaminK1Per100g": 6.84,
  "vitaminK2Per100g": 0,
  "folatePer100g": 32.48,
  "vitaminB1Per100g": 0.06,
  "vitaminB2Per100g": 0.05,
  "vitaminB3Per100g": 0.45,
  "vitaminB5Per100g": 0.6,
  "vitaminB6Per100g": 0.11,
  "vitaminB7Per100g": 0.88,
  "vitaminB9Per100g": 32.48,
  "vitaminCPer100g": 5.39,
  "carotenoidsPer100g": 1117.93,
  "standardServings": {
    "serving": 100
  },
  "source": "asc_manual",
  "primaryCategory": "uncategorized",
  "tags": [],
  "searchTerms": [
    "moti mahal dal (urad rajmah mix dal)",
    "moti",
    "mahal",
    "dal",
    "(urad",
    "rajmah",
    "mix",
    "dal)"
  ]
}