{
  "id": "plain-khitchdi-plain-khichri-khichdi",
  "code": "BFP144",
  "name": "Plain khitchdi (Plain khichri/khichdi)",
  "alternateNames": [],
  "caloriesPer100g": 57.03,
  "energyKj": 238.08,
  "proteinPer100g": 1.72,
  "carbsPer100g": 10.04,
  "fatPer100g": 1.01,
  "fiberPer100g": 0.85,
  "freeSugarPer100g": 0.12,
  "saturatedFatPer100g": 538.13,
  "monounsaturatedFatPer100g": 250.79,
  "polyunsaturatedFatPer100g": 96.34,
  "cholesterolPer100g": 2.14,
  "calciumPer100g": 5.05,
  "phosphorusPer100g": 30.71,
  "magnesiumPer100g": 9.97,
  "sodiumPer100g": 37.14,
  "potassiumPer100g": 69.32,
  "ironPer100g": 0.31,
  "copperPer100g": 0.07,
  "zincPer100g": 0.22,
  "seleniumPer100g": 1.88,
  "chromiumPer100g": 0,
  "manganesePer100g": 0.16,
  "molybdenumPer100g": 0.04,
  "vitaminAPer100g": 8.03,
  "vitaminEPer100g": 0.07,
  "vitaminD2Per100g": 0.14,
  "vitaminD3Per100g": 0,
  "vitaminDPer100g": 0.14,
  "vitaminK1Per100g": 1.92,
  "vitaminK2Per100g": 0,
  "folatePer100g": 4.56,
  "vitaminB1Per100g": 0.03,
  "vitaminB2Per100g": 0.01,
  "vitaminB3Per100g": 0.34,
  "vitaminB5Per100g": 0.12,
  "vitaminB6Per100g": 0.03,
  "vitaminB7Per100g": 0.08,
  "vitaminB9Per100g": 4.56,
  "vitaminCPer100g": 0.14,
  "carotenoidsPer100g": 102.54,
  "standardServings": {
    "serving": 100
  },
  "source": "bfp_manual",
  "primaryCategory": "uncategorized",
  "tags": [],
  "searchTerms": [
    "plain khitchdi (plain khichri/khichdi)",
    "plain",
    "khitchdi",
    "(plain",
    "khichri/khichdi)"
  ]
}