{
  "id": "potato-pakora-pakoda-aloo-pakoda",
  "code": "ASC351",
  "name": "Potato pakora/pakoda (Aloo pakoda)",
  "alternateNames": [],
  "caloriesPer100g": 677.19,
  "energyKj": 2788.18,
  "proteinPer100g": 1.9,
  "carbsPer100g": 6.04,
  "fatPer100g": 71.84,
  "fiberPer100g": 1.03,
  "freeSugarPer100g": 0.22,
  "saturatedFatPer100g": 8628.82,
  "monounsaturatedFatPer100g": 14729.45,
  "polyunsaturatedFatPer100g": 45466.16,
  "cholesterolPer100g": 0,
  "calciumPer100g": 6.59,
  "phosphorusPer100g": 21.94,
  "magnesiumPer100g": 7.85,
  "sodiumPer100g": 63.38,
  "potassiumPer100g": 90.01,
  "ironPer100g": 0.38,
  "copperPer100g": 0.04,
  "zincPer100g": 0.15,
  "seleniumPer100g": 0.39,
  "chromiumPer100g": 0,
  "manganesePer100g": 0.14,
  "molybdenumPer100g": 0,
  "vitaminAPer100g": 0,
  "vitaminEPer100g": 35.37,
  "vitaminD2Per100g": 0.02,
  "vitaminD3Per100g": 0,
  "vitaminDPer100g": 0.02,
  "vitaminK1Per100g": 5.53,
  "vitaminK2Per100g": 0,
  "folatePer100g": 16.18,
  "vitaminB1Per100g": 0.04,
  "vitaminB2Per100g": 0.01,
  "vitaminB3Per100g": 0.28,
  "vitaminB5Per100g": 0.14,
  "vitaminB6Per100g": 0.05,
  "vitaminB7Per100g": 0.78,
  "vitaminB9Per100g": 16.18,
  "vitaminCPer100g": 2.75,
  "carotenoidsPer100g": 46.95,
  "standardServings": {
    "serving": 100
  },
  "source": "asc_manual",
  "primaryCategory": "uncategorized",
  "tags": [],
  "searchTerms": [
    "potato pakora/pakoda (aloo pakoda)",
    "potato",
    "pakora/pakoda",
    "(aloo",
    "pakoda)"
  ]
}