{
  "id": "semolina-ladoo-with-coconut-suji-rava-aur-nariyal-ke-ladoo",
  "code": "ASC342",
  "name": "Semolina ladoo with coconut (Suji/Rava aur nariyal ke ladoo )",
  "alternateNames": [],
  "caloriesPer100g": 464.43,
  "energyKj": 1942.7,
  "proteinPer100g": 5.68,
  "carbsPer100g": 50.9,
  "fatPer100g": 27.03,
  "fiberPer100g": 6.69,
  "freeSugarPer100g": 27.32,
  "saturatedFatPer100g": 17143.41,
  "monounsaturatedFatPer100g": 4407.23,
  "polyunsaturatedFatPer100g": 941.52,
  "cholesterolPer100g": 33.81,
  "calciumPer100g": 26.72,
  "phosphorusPer100g": 90.08,
  "magnesiumPer100g": 34.77,
  "sodiumPer100g": 9.06,
  "potassiumPer100g": 264.85,
  "ironPer100g": 1.83,
  "copperPer100g": 0.36,
  "zincPer100g": 1.08,
  "seleniumPer100g": 9.07,
  "chromiumPer100g": 0.01,
  "manganesePer100g": 1.14,
  "molybdenumPer100g": 0.04,
  "vitaminAPer100g": 126.74,
  "vitaminEPer100g": 2.13,
  "vitaminD2Per100g": 2.96,
  "vitaminD3Per100g": 0,
  "vitaminDPer100g": 2.96,
  "vitaminK1Per100g": 1.03,
  "vitaminK2Per100g": 0,
  "folatePer100g": 14.32,
  "vitaminB1Per100g": 0.11,
  "vitaminB2Per100g": 0.03,
  "vitaminB3Per100g": 0.54,
  "vitaminB5Per100g": 0.33,
  "vitaminB6Per100g": 0.07,
  "vitaminB7Per100g": 0.51,
  "vitaminB9Per100g": 14.32,
  "vitaminCPer100g": 0.14,
  "carotenoidsPer100g": 402.22,
  "standardServings": {
    "serving": 100
  },
  "source": "asc_manual",
  "primaryCategory": "uncategorized",
  "tags": [],
  "searchTerms": [
    "semolina ladoo with coconut (suji/rava aur nariyal ke ladoo )",
    "semolina",
    "ladoo",
    "with",
    "coconut",
    "(suji/rava",
    "aur",
    "nariyal",
    "ke"
  ]
}