{
  "id": "sour-cream-potato-salad",
  "code": "BFP300",
  "name": "Sour cream potato salad",
  "alternateNames": [],
  "caloriesPer100g": 121.9,
  "energyKj": 505.89,
  "proteinPer100g": 2.89,
  "carbsPer100g": 9.05,
  "fatPer100g": 8.13,
  "fiberPer100g": 1.21,
  "freeSugarPer100g": 0.84,
  "saturatedFatPer100g": 744.99,
  "monounsaturatedFatPer100g": 3418.24,
  "polyunsaturatedFatPer100g": 1550.73,
  "cholesterolPer100g": 47.29,
  "calciumPer100g": 23.25,
  "phosphorusPer100g": 55.18,
  "magnesiumPer100g": 19.19,
  "sodiumPer100g": 102.66,
  "potassiumPer100g": 367.59,
  "ironPer100g": 0.9,
  "copperPer100g": 0.12,
  "zincPer100g": 0.42,
  "seleniumPer100g": 4.91,
  "chromiumPer100g": 0,
  "manganesePer100g": 0.14,
  "molybdenumPer100g": 0.02,
  "vitaminAPer100g": 26.98,
  "vitaminEPer100g": 1.67,
  "vitaminD2Per100g": 0.3,
  "vitaminD3Per100g": 0.09,
  "vitaminDPer100g": 0.39,
  "vitaminK1Per100g": 4.64,
  "vitaminK2Per100g": 1.61,
  "folatePer100g": 23.36,
  "vitaminB1Per100g": 0.05,
  "vitaminB2Per100g": 0.04,
  "vitaminB3Per100g": 0.67,
  "vitaminB5Per100g": 0.43,
  "vitaminB6Per100g": 0.1,
  "vitaminB7Per100g": 3.06,
  "vitaminB9Per100g": 23.36,
  "vitaminCPer100g": 16.43,
  "carotenoidsPer100g": 348.62,
  "standardServings": {
    "serving": 100
  },
  "source": "bfp_manual",
  "primaryCategory": "uncategorized",
  "tags": [],
  "searchTerms": [
    "sour cream potato salad",
    "sour",
    "cream",
    "potato",
    "salad"
  ]
}