{
  "id": "spinach-burfi-palak-burfi",
  "code": "ASC466",
  "name": "Spinach burfi (Palak burfi)",
  "alternateNames": [],
  "caloriesPer100g": 121.17,
  "energyKj": 508.27,
  "proteinPer100g": 2.71,
  "carbsPer100g": 12.76,
  "fatPer100g": 6.81,
  "fiberPer100g": 1.17,
  "freeSugarPer100g": 12.12,
  "saturatedFatPer100g": 4185.8,
  "monounsaturatedFatPer100g": 1406.68,
  "polyunsaturatedFatPer100g": 296.02,
  "cholesterolPer100g": 5.65,
  "calciumPer100g": 93.68,
  "phosphorusPer100g": 70.87,
  "magnesiumPer100g": 33.14,
  "sodiumPer100g": 27.77,
  "potassiumPer100g": 268.78,
  "ironPer100g": 1.05,
  "copperPer100g": 0.1,
  "zincPer100g": 0.38,
  "seleniumPer100g": 1.89,
  "chromiumPer100g": 0.01,
  "manganesePer100g": 0.43,
  "molybdenumPer100g": 0.01,
  "vitaminAPer100g": 21.16,
  "vitaminEPer100g": 0.8,
  "vitaminD2Per100g": 0.14,
  "vitaminD3Per100g": 0,
  "vitaminDPer100g": 0.14,
  "vitaminK1Per100g": 93.35,
  "vitaminK2Per100g": 0,
  "folatePer100g": 45.48,
  "vitaminB1Per100g": 0.06,
  "vitaminB2Per100g": 0.09,
  "vitaminB3Per100g": 0.16,
  "vitaminB5Per100g": 0.26,
  "vitaminB6Per100g": 0.07,
  "vitaminB7Per100g": 2.36,
  "vitaminB9Per100g": 45.48,
  "vitaminCPer100g": 9.84,
  "carotenoidsPer100g": 2904.3,
  "standardServings": {
    "serving": 100
  },
  "source": "asc_manual",
  "primaryCategory": "uncategorized",
  "tags": [],
  "searchTerms": [
    "spinach burfi (palak burfi)",
    "spinach",
    "burfi",
    "(palak",
    "burfi)"
  ]
}