{
  "id": "starfruit-preserves",
  "code": "OSR048",
  "name": "Starfruit preserves ",
  "alternateNames": [],
  "caloriesPer100g": 128.93,
  "energyKj": 549.14,
  "proteinPer100g": 0.24,
  "carbsPer100g": 33.62,
  "fatPer100g": 0.12,
  "fiberPer100g": 0.78,
  "freeSugarPer100g": 33.47,
  "saturatedFatPer100g": 10.37,
  "monounsaturatedFatPer100g": 9.31,
  "polyunsaturatedFatPer100g": 57.51,
  "cholesterolPer100g": 0,
  "calciumPer100g": 5.24,
  "phosphorusPer100g": 4,
  "magnesiumPer100g": 4.09,
  "sodiumPer100g": 2.06,
  "potassiumPer100g": 49.72,
  "ironPer100g": 0.2,
  "copperPer100g": 0.06,
  "zincPer100g": 0.1,
  "seleniumPer100g": 0.2,
  "chromiumPer100g": 0.01,
  "manganesePer100g": 0.02,
  "molybdenumPer100g": 0,
  "vitaminAPer100g": 0,
  "vitaminEPer100g": 0.11,
  "vitaminD2Per100g": 0.27,
  "vitaminD3Per100g": 0,
  "vitaminDPer100g": 0.27,
  "vitaminK1Per100g": 0.55,
  "vitaminK2Per100g": 0,
  "folatePer100g": 2.66,
  "vitaminB1Per100g": 0.02,
  "vitaminB2Per100g": 0.01,
  "vitaminB3Per100g": 0.1,
  "vitaminB5Per100g": 0.08,
  "vitaminB6Per100g": 0.02,
  "vitaminB7Per100g": 0.04,
  "vitaminB9Per100g": 2.66,
  "vitaminCPer100g": 10.86,
  "carotenoidsPer100g": 42.28,
  "standardServings": {
    "serving": 100
  },
  "source": "open_source_recipes",
  "primaryCategory": "uncategorized",
  "tags": [],
  "searchTerms": [
    "starfruit preserves ",
    "starfruit",
    "preserves"
  ]
}