{
  "id": "vegetable-poha",
  "code": "BFP045",
  "name": "Vegetable poha",
  "alternateNames": [],
  "caloriesPer100g": 180.52,
  "energyKj": 751.96,
  "proteinPer100g": 4.89,
  "carbsPer100g": 21.52,
  "fatPer100g": 8.07,
  "fiberPer100g": 3.76,
  "freeSugarPer100g": 1.4,
  "saturatedFatPer100g": 1165.72,
  "monounsaturatedFatPer100g": 2322.69,
  "polyunsaturatedFatPer100g": 4183.58,
  "cholesterolPer100g": 0,
  "calciumPer100g": 28.01,
  "phosphorusPer100g": 96.29,
  "magnesiumPer100g": 48.59,
  "sodiumPer100g": 418.02,
  "potassiumPer100g": 223.09,
  "ironPer100g": 1.92,
  "copperPer100g": 0.19,
  "zincPer100g": 0.81,
  "seleniumPer100g": 2.28,
  "chromiumPer100g": 0.01,
  "manganesePer100g": 0.54,
  "molybdenumPer100g": 0.16,
  "vitaminAPer100g": 0,
  "vitaminEPer100g": 2.85,
  "vitaminD2Per100g": 4.13,
  "vitaminD3Per100g": 0,
  "vitaminDPer100g": 4.13,
  "vitaminK1Per100g": 15.45,
  "vitaminK2Per100g": 0,
  "folatePer100g": 22.28,
  "vitaminB1Per100g": 0.11,
  "vitaminB2Per100g": 0.05,
  "vitaminB3Per100g": 1.35,
  "vitaminB5Per100g": 0.37,
  "vitaminB6Per100g": 0.09,
  "vitaminB7Per100g": 1.02,
  "vitaminB9Per100g": 22.28,
  "vitaminCPer100g": 7.37,
  "carotenoidsPer100g": 2675.12,
  "standardServings": {
    "serving": 100
  },
  "source": "bfp_manual",
  "primaryCategory": "uncategorized",
  "tags": [],
  "searchTerms": [
    "vegetable poha",
    "vegetable",
    "poha"
  ]
}